coopbugger/__init__.py
coopbugger/monitoredclass.py
coopbugger-0.4.dist-info/LICENSE
coopbugger-0.4.dist-info/METADATA
coopbugger-0.4.dist-info/WHEEL
coopbugger-0.4.dist-info/top_level.txt
coopbugger-0.4.dist-info/RECORD
